convoviz/__init__.py
convoviz/__main__.py
convoviz/analysis/__init__.py
convoviz/analysis/graphs.py
convoviz/analysis/wordcloud.py
convoviz/assets/colormaps.txt
convoviz/assets/fonts/AmaticSC-Regular.ttf
convoviz/assets/fonts/ArchitectsDaughter-Regular.ttf
convoviz/assets/fonts/BebasNeue-Regular.ttf
convoviz/assets/fonts/Borel-Regular.ttf
convoviz/assets/fonts/Courgette-Regular.ttf
convoviz/assets/fonts/CroissantOne-Regular.ttf
convoviz/assets/fonts/Handjet-Regular.ttf
convoviz/assets/fonts/IndieFlower-Regular.ttf
convoviz/assets/fonts/Kalam-Regular.ttf
convoviz/assets/fonts/Lobster-Regular.ttf
convoviz/assets/fonts/MartianMono-Regular.ttf
convoviz/assets/fonts/MartianMono-Thin.ttf
convoviz/assets/fonts/Montserrat-Regular.ttf
convoviz/assets/fonts/Mooli-Regular.ttf
convoviz/assets/fonts/Pacifico-Regular.ttf
convoviz/assets/fonts/PlayfairDisplay-Regular.ttf
convoviz/assets/fonts/Raleway-Regular.ttf
convoviz/assets/fonts/RobotoMono-Regular.ttf
convoviz/assets/fonts/RobotoMono-Thin.ttf
convoviz/assets/fonts/RobotoSlab-Regular.ttf
convoviz/assets/fonts/RobotoSlab-Thin.ttf
convoviz/assets/fonts/Ruwudu-Regular.ttf
convoviz/assets/fonts/Sacramento-Regular.ttf
convoviz/assets/fonts/SedgwickAveDisplay-Regular.ttf
convoviz/assets/fonts/ShadowsIntoLight-Regular.ttf
convoviz/assets/fonts/TitilliumWeb-Regular.ttf
convoviz/assets/fonts/Yellowtail-Regular.ttf
convoviz/assets/fonts/YsabeauOffice-Regular.ttf
convoviz/assets/fonts/YsabeauSC-Regular.ttf
convoviz/assets/fonts/YsabeauSC-Thin.ttf
convoviz/assets/fonts/Zeyada-Regular.ttf
convoviz/assets/stopwords.txt
convoviz/cli.py
convoviz/config.py
convoviz/exceptions.py
convoviz/interactive.py
convoviz/io/__init__.py
convoviz/io/assets.py
convoviz/io/loaders.py
convoviz/io/writers.py
convoviz/logging_config.py
convoviz/models/__init__.py
convoviz/models/collection.py
convoviz/models/conversation.py
convoviz/models/message.py
convoviz/models/node.py
convoviz/pipeline.py
convoviz/py.typed
convoviz/renderers/__init__.py
convoviz-0.4.5.dist-info/WHEEL
convoviz-0.4.5.dist-info/entry_points.txt
convoviz-0.4.5.dist-info/METADATA
convoviz-0.4.5.dist-info/RECORD
