Metadata-Version: 2.4
Name: convoviz
Version: 0.4.5
Summary: Convert your ChatGPT export (ZIP) into clean Markdown text files with inline media, and generate data visualizations like word clouds and usage graphs.
Keywords: markdown,chatgpt,openai,visualization,analytics,json,export,data-analysis,obsidian
Author: Mohamed Cheikh Sidiya
Author-email: Mohamed Cheikh Sidiya <mohamedcheikhsidiya77@gmail.com>
License-Expression: MIT
Classifier: License :: OSI Approved :: MIT License
Classifier: Programming Language :: Python :: 3
Classifier: Programming Language :: Python :: 3.12
Requires-Dist: orjson>=3.11.5
Requires-Dist: pydantic>=2.12.5
Requires-Dist: pydantic-settings>=2.7.0
Requires-Dist: questionary>=2.1.1
Requires-Dist: rich>=14.2.0
Requires-Dist: tqdm>=4.67.1
Requires-Dist: typer>=0.21.0
Requires-Dist: nltk>=3.9.2 ; extra == 'viz'
Requires-Dist: wordcloud>=1.9.5 ; extra == 'viz'
Requires-Python: >=3.12
Project-URL: Repository, https://github.com/mohamed-chs/convoviz
Provides-Extra: viz
